mathifyOS/__init__.py
mathifyOS-3.11.0.dist-info/METADATA
mathifyOS-3.11.0.dist-info/WHEEL
mathifyOS-3.11.0.dist-info/top_level.txt
mathifyOS-3.11.0.dist-info/RECORD
