Metadata-Version: 2.1
Name: mathifyOS
Version: 3.11.0
Summary: Makes life easier!
Home-page: UNKNOWN
Author: Daniel Duchouquette
Author-email: <danpersonguything@email.com>
License: UNKNOWN
Keywords: python,Simple,Math,OS
Platform: UNKNOWN
Classifier: Development Status :: 3 - Alpha
Classifier: Intended Audience :: Education
Classifier: Programming Language :: Python :: 2
Classifier: Programming Language :: Python :: 3
Classifier: Operating System :: MacOS :: MacOS X
Classifier: Operating System :: Microsoft :: Windows
